pourover/__init__.py
pourover/__version__.py
pourover/exceptions.py
pourover/functions.py
pourover/models.py
pourover/utils.py
pourover-0.1b8.dist-info/LICENSE
pourover-0.1b8.dist-info/METADATA
pourover-0.1b8.dist-info/WHEEL
pourover-0.1b8.dist-info/top_level.txt
pourover-0.1b8.dist-info/RECORD
