Metadata-Version: 2.1
Name: pourover
Version: 0.1b8
Summary: Python CEF Parsing for Lizard People
Home-page: https://github.com/zthart/pourover
Author: Zach Hart
Author-email: zach@csh.rit.edu
Maintainer: Zach Hart
Maintainer-email: zach@csh.rit.edu
License: UNKNOWN
Keywords: CEF parsing formatting log messages
Platform: any
Classifier: Development Status :: 4 - Beta
Classifier: Intended Audience :: Developers
Classifier: Topic :: System :: Logging
Classifier: Natural Language :: English
Classifier: License :: OSI Approved :: Apache Software License
Classifier: Programming Language :: Python
Classifier: Programming Language :: Python :: 3
Classifier: Programming Language :: Python :: 3.6
Classifier: Programming Language :: Python :: 3.7
Classifier: Programming Language :: Python :: Implementation :: CPython
Classifier: Programming Language :: Python :: Implementation :: PyPy
